hat/gateway/runner.py
hat/gateway/devices/iec103/master.py
hat/gateway/devices/modbus/__init__.py
hat/gateway/devices/modbus/master/eventer_client.py
hat/gateway/main.py
hat/gateway/devices/modbus/master/connection.py
hat/gateway/devices/snmp/__init__.py
hat/gateway/__main__.py
hat/gateway/adminer/__init__.py
hat/gateway/devices/modbus/master/device.py
hat/gateway/adminer/server.py
hat/gateway/devices/iec103/__init__.py
hat/gateway/devices/modbus/master/remote_device.py
hat/gateway/devices/iec104/slave.py
hat/gateway/adminer/common.py
hat/gateway/devices/smpp/client.py
hat/gateway/devices/iec104/ssl.py
hat/gateway/devices/ping.py
hat/gateway/common.py
hat/gateway/__init__.py
hat/gateway/devices/iec101/master.py
hat/gateway/devices/__init__.py
hat/gateway/devices/iec101/slave.py
hat/gateway/adminer/client.py
hat/gateway/devices/iec101/__init__.py
hat/gateway/devices/modbus/master/__init__.py
hat/gateway/devices/iec101/common.py
hat/gateway/sbs_repo.json
hat/gateway/devices/iec104/common.py
hat/gateway/devices/snmp/manager.py
hat/gateway/devices/iec61850/client.py
hat/gateway/json_schema_repo.json
hat/gateway/devices/snmp/trap_listener.py
hat/gateway/devices/smpp/__init__.py
hat/gateway/engine.py
hat/gateway/adminer_server.py
hat/gateway/devices/iec104/__init__.py
hat/gateway/devices/iec61850/__init__.py
hat/gateway/devices/iec104/master.py
hat_gateway-0.6.32.dist-info/LICENSE
hat_gateway-0.6.32.dist-info/entry_points.txt
hat_gateway-0.6.32.dist-info/METADATA
hat_gateway-0.6.32.dist-info/WHEEL
hat_gateway-0.6.32.dist-info/RECORD
