Metadata-Version: 2.1
Name: hat-gateway
Version: 0.6.32
Summary: Hat gateway
License: Apache-2.0
Provides-Extra: dev
Requires-Dist: appdirs ~=1.4.4
Requires-Dist: hat-aio ~=0.7.12
Requires-Dist: hat-drivers ~=0.9.23
Requires-Dist: hat-event ~=0.9.36
Requires-Dist: hat-json ~=0.6.3
Requires-Dist: hat-monitor ~=0.8.19
Requires-Dist: hat-sbs ~=0.7.5
Requires-Dist: hat-util ~=0.6.20
Requires-Dist: hat-doit ~=0.16.2; extra == 'dev'
Requires-Dist: psutil >=5.9.8; extra == 'dev'
Requires-Dist: sphinxcontrib-plantuml >=0.27; extra == 'dev'
Requires-Dist: sphinxcontrib-programoutput >=0.17; extra == 'dev'
Requires-Python: >=3.10
Project-URL: Homepage, http://hat-open.com
Project-URL: Repository, https://github.com/hat-open/hat-gateway.git
Project-URL: Documentation, http://hat-gateway.hat-open.com
